fstorage/__init__.py
fstorage/client/__init__.py
fstorage/client/base_client.py
fstorage/client/asynch/__init__.py
fstorage/client/asynch/client.py
fstorage/client/synch/__init__.py
fstorage/client/synch/client.py
fstorage/server/__init__.py
fstorage/server/app.py
fstorage/server/app_params.py
fstorage/server/storage/__init__.py
fstorage/server/storage/exceptions.py
fstorage/server/storage/models.py
fstorage/server/storage/router.py
fstorage-0.0.3.dist-info/LICENSE
fstorage-0.0.3.dist-info/METADATA
fstorage-0.0.3.dist-info/WHEEL
fstorage-0.0.3.dist-info/top_level.txt
fstorage-0.0.3.dist-info/RECORD
