Metadata-Version: 2.1
Name: fstorage
Version: 0.0.3
Summary: Fstorage, Secure file storage, SYNC/ASYNC clients, easy to learn, fast to code.
Home-page: https://github.com/ispaneli/fstorage
Author: Ilya Antonov
Author-email: ispanelki@gmail.com
Project-URL: Issue Tracker, https://github.com/ispaneli/fstorage/issues
Project-URL: Source, https://github.com/ispaneli/fstorage/tree/master/src/fstorage
Project-URL: Say Thanks!, http://saythanks.io/to/ispanelki
Project-URL: Documentation, https://github.com/ispaneli/fstorage
Keywords: file,files,storage,security,sync,synch,async,asynch,server,client,fastapi,aiohttp,requests
Classifier: Development Status :: 4 - Beta
Classifier: Environment :: Web Environment
Classifier: Framework :: AnyIO
Classifier: Framework :: FastAPI
Classifier: Framework :: aiohttp
Classifier: Intended Audience :: Customer Service
Classifier: Intended Audience :: Developers
Classifier: Intended Audience :: Information Technology
Classifier: Intended Audience :: System Administrators
Classifier: License :: OSI Approved :: MIT License
Classifier: Natural Language :: English
Classifier: Natural Language :: Russian
Classifier: Operating System :: OS Independent
Classifier: Programming Language :: Python
Classifier: Programming Language :: Python :: 3
Classifier: Programming Language :: Python :: 3 :: Only
Classifier: Programming Language :: Python :: 3.8
Classifier: Programming Language :: Python :: 3.9
Classifier: Programming Language :: Python :: 3.10
Classifier: Programming Language :: Python :: 3.11
Classifier: Topic :: Communications :: File Sharing
Classifier: Topic :: Database
Classifier: Topic :: Database :: Database Engines/Servers
Classifier: Topic :: Internet
Classifier: Topic :: Internet :: File Transfer Protocol (FTP)
Classifier: Topic :: Internet :: WWW/HTTP
Classifier: Topic :: Internet :: WWW/HTTP :: HTTP Servers
Classifier: Topic :: Security
Classifier: Topic :: Security :: Cryptography
Classifier: Topic :: Software Development :: Libraries
Classifier: Topic :: Software Development :: Libraries :: Python Modules
Classifier: Topic :: System
Classifier: Topic :: System :: Filesystems
Classifier: Typing :: Typed
Requires-Python: <4,>=3.8
License-File: LICENSE
Provides-Extra: async_client
Requires-Dist: aiohttp (>=3.8.4) ; extra == 'async_client'
Provides-Extra: server
Requires-Dist: python-multipart (>=0.0.6) ; extra == 'server'
Requires-Dist: uvicorn (>=0.21.0) ; extra == 'server'
Requires-Dist: fastapi (>=0.94.0) ; extra == 'server'
Requires-Dist: sqlmodel (>=0.0.8) ; extra == 'server'
Requires-Dist: asyncpg (>=0.27.0) ; extra == 'server'
Requires-Dist: greenlet (>=2.0.2) ; extra == 'server'
Provides-Extra: sync_client
Requires-Dist: requests (>=2.28.2) ; extra == 'sync_client'
